Micro_GC_Fusion_API/__init__.py
Micro_GC_Fusion_API/fusion.py
Micro_GC_Fusion_API-0.0.7.dist-info/LICENSE
Micro_GC_Fusion_API-0.0.7.dist-info/METADATA
Micro_GC_Fusion_API-0.0.7.dist-info/WHEEL
Micro_GC_Fusion_API-0.0.7.dist-info/top_level.txt
Micro_GC_Fusion_API-0.0.7.dist-info/RECORD
