Metadata-Version: 2.1
Name: Micro_GC_Fusion_API
Version: 0.0.7
Summary: Micro GC Fusion API
License: Copyright <2024> <COPYRIGHT Shawn Wilson>
Project-URL: Homepage, https://inficon.com
Keywords: chromatography,GC,inficon,gas chromatography
Requires-Python: >=3.8
License-File: LICENSE
Requires-Dist: requests
Requires-Dist: importlib-metadata; python_version >= "3.8"
